rekt/__init__.py
rekt/httputils.py
rekt/service.py
rekt/utils.py
rekt/specs/googlemaps.yaml
rekt/specs/googleplaces.yaml
rekt-0.2015.11.6.dist-info/DESCRIPTION.rst
rekt-0.2015.11.6.dist-info/METADATA
rekt-0.2015.11.6.dist-info/RECORD
rekt-0.2015.11.6.dist-info/WHEEL
rekt-0.2015.11.6.dist-info/entry_points.txt
rekt-0.2015.11.6.dist-info/metadata.json
rekt-0.2015.11.6.dist-info/top_level.txt
